minecraft_seed_generator.py
minecraft_seed_generator-0.1.1.dist-info/WHEEL
minecraft_seed_generator-0.1.1.dist-info/METADATA
minecraft_seed_generator-0.1.1.dist-info/RECORD
