Metadata-Version: 2.1
Name: minecraft-seed-generator
Version: 0.1.1
Summary: GenerateSeed(5)
Author: Fab4key
Author-email: fab4key@gmail.com
Requires-Python: >=3.7,<4.0
Classifier: Programming Language :: Python :: 3
Classifier: Programming Language :: Python :: 3.7
Classifier: Programming Language :: Python :: 3.8
